Workbook

Sheet Inputs
A1: Jannat Garments and Jobworks - Input Data (monthly)
A2: Blue = input from factory visit / stated assumption. Edit blue cells only; all other sheets recalculate.
A4: Item | B4: Value | C4: Source / Note
A5: Units produced and sold per month | B5: 22000 | C5: Assumption: lower end of owner's stated capacity 22k-27k
A6: Selling (job-work) rate per unit (Rs) | B6: 48 | C6: Owner: approx Rs 48 per unit, fixed by pattern
A7: Maximum capacity (units/month) | B7: 27000 | C7: Owner: 22k-27k units
A8: Thread (Rs) | B8: 50000 | C8: Owner: approx 50k
A9: Colour / dye (Rs) | B9: 50000 | C9: Owner: approx 50k
A10: Finishing, label & lace (Rs) | B10: 50000 | C10: Balance of Rs 1.5L total material cost
A11: Making (labour) cost per unit (Rs) | B11: 21 | C11: Owner: Rs 20-22 per unit (midpoint)
A12: Gross wastage (Rs) | B12: 12500 | C12: Owner: Rs 10k-15k (midpoint)
A13: Waste recovery / scrap credit (Rs) | B13: 1600 | C13: Owner: Rs 1,500-1,700 recovered (midpoint)
A14: Electricity (Rs) | B14: 45000 | C14: Owner: Rs 45k
A15: Number of helpers | B15: 5 | C15: Owner: 5 helpers
A16: Salary per helper (Rs) | B16: 12000 | C16: Owner: Rs 12k each
... A23: Miscellaneous overheads (Rs) | B23: 25000 | C23: ESTIMATE - rent share, packing, transport, stationery

Sheet Cost Sheet
A1: Cost Sheet - Boys Shirts (excluding buttons)
A2: Period: one month | Output: units per Inputs sheet
A4: Particulars | B4: Amount (Rs) | C4: Per Unit (Rs)
A5: A. DIRECT MATERIAL (consumables)
A6: Thread | B6: =Inputs!$B$8 -> 50000 | C6: =B6/Inputs!$B$5 -> 2.2727273
A7: Colour / dye | B7: =Inputs!$B$9 -> 50000 | C7: =B7/Inputs!$B$5 -> 2.2727273
A8: Finishing, label & lace | B8: =Inputs!$B$10 -> 50000 | C8: =B8/Inputs!$B$5 -> 2.2727273
A9: Total Direct Material | B9: =SUM(B6:B8) -> 150000 | C9: =B9/Inputs!$B$5 -> 6.8181818
A10: B. DIRECT LABOUR
A11: Tailors' making charges | B11: =Inputs!$B$11*Inputs!$B$5 -> 462000 | C11: =B11/Inputs!$B$5 -> 21
A12: PRIME COST (A + B) | B12: =B9+B11 -> 612000 | C12: =B12/Inputs!$B$5 -> 27.818182
A13: C. FACTORY OVERHEADS
A14: Electricity | B14: =Inputs!$B$14 -> 45000 | C14: =B14/Inputs!$B$5 -> 2.0454545
A15: Helpers' salaries | B15: =Inputs!$B$15*Inputs!$B$16 -> 60000 | C15: =B15/Inputs!$B$5 -> 2.7272727
A16: Master tailor / supervisor salary | B16: =Inputs!$B$17 -> 50000 | C16: =B16/Inputs!$B$5 -> 2.2727273
A17: Machine repairs & maintenance | B17: =Inputs!$B$18 -> 45000 | C17: =B17/Inputs!$B$5 -> 2.0454545
A18: Depreciation on machines (monthly) | B18: =Inputs!$B$19*Inputs!$B$20*Inputs!$B$21/12 -> 24000 | C18: =B18/Inputs!$B$5 -> 1.0909091
A19: Wastage (net of scrap recovery) | B19: =Inputs!$B$12-Inputs!$B$13 -> 10900 | C19: =B19/Inputs!$B$5 -> 0.49545455
A20: Total Factory Overheads | B20: =SUM(B14:B19) -> 234900 | C20: =B20/Inputs!$B$5 -> 10.677273
A21: FACTORY COST (Prime + Factory OH) | B21: =B12+B20 -> 846900 | C21: =B21/Inputs!$B$5 -> 38.495455
A22: D. ADMINISTRATIVE OVERHEADS
A23: Tax | B23: =Inputs!$B$22 -> 32500 | C23: =B23/Inputs!$B$5 -> 1.4772727
A24: Miscellaneous overheads (estimate) | B24: =Inputs!$B$23 -> 25000 | C24: =B24/Inputs!$B$5 -> 1.1363636
A25: Total Administrative Overheads | B25: =B23+B24 -> 57500 | C25: =B25/Inputs!$B$5 -> 2.6136364
A26: TOTAL COST OF PRODUCTION (COST OF SALES) | B26: =B21+B25 -> 904400 | C26: =B26/Inputs!$B$5 -> 41.109091
A27: Sales revenue | B27: =Inputs!$B$5*Inputs!$B$6 -> 1056000 | C27: =B27/Inputs!$B$5 -> 48
A28: PROFIT | B28: =B27-B26 -> 151600 | C28: =B28/Inputs!$B$5 -> 6.8909091
A31: Profit margin on sales | B31: =B28/B27 -> 0.14356061

Sheet CVP
A1: Cost-Volume-Profit Analysis
A3: Particulars | B3: Amount | C3: Note
A4: Variable cost per unit - material | B4: ='Cost Sheet'!C9 -> 6.8181818
A5: Variable cost per unit - labour | B5: ='Cost Sheet'!C11 -> 21
A6: Variable cost per unit - net wastage | B6: ='Cost Sheet'!C19 -> 0.49545455
A7: Total variable cost per unit | B7: =SUM(B4:B6) -> 28.313636
A8: Selling price per unit | B8: =Inputs!$B$6 -> 48
A9: Contribution per unit | B9: =B8-B7 -> 19.686364
A10: P/V ratio | B10: =B9/B8 -> 0.41013258
A11: Total fixed costs (monthly) | B11: ='Cost Sheet'!B14+'Cost Sheet'!B15+'Cost Sheet'!B16+'Cost Sheet'!B17+'Cost Sheet'!B18+'Cost Sheet'!B25 -> 281500 | C11: Electricity, helpers, master tailor, repairs, depreciation, admin
A12: Break-even point (units) | B12: =B11/B9 -> 14299.238
A13: Break-even point (sales value, Rs) | B13: =B12*B8 -> 686363.43
A14: Actual units | B14: =Inputs!$B$5 -> 22000
A15: Margin of safety (units) | B15: =B14-B12 -> 7700.7619
A16: Margin of safety (%) | B16: =B15/B14 -> 0.35003463
A17: Total contribution | B17: =B14*B9 -> 433100
A18: Profit | B18: =B17-B11 -> 151600
A19: Degree of operating leverage | B19: =B17/B18 -> 2.8568602
A20: Break-even as % of capacity | B20: =B12/Inputs!$B$7 -> 0.52960141
A23: Sensitivity / What-if scenarios
A24: Scenario | B24: Contribution/unit | C24: Fixed cost | D24: BEP (units) | E24: BEP (Rs) | F24: Profit at actual units
A25: Base case | B25: =B9 -> 19.686364 | C25: =B11 -> 281500 | D25: =C25/B25 -> 14299.238 | E25: =D25*B8 -> 686363.43 | F25: =B25*B14-C25 -> 151600
A26: Labour rate +10% | B26: =B9-0.1*B5 -> 17.586364 | C26: =B11 -> 281500 | D26: =C26/B26 -> 16006.72 | E26: =D26*B8 -> 768322.56 | F26: =B26*B14-C26 -> 105400
A27: Selling price Rs 45 | B27: =45-B7 -> 16.686364 | C27: =B11 -> 281500 | D27: =C27/B27 -> 16870.063 | E27: =D27*45 -> 759152.82 | F27: =B27*B14-C27 -> 85600
A28: Selling price Rs 50 | B28: =50-B7 -> 21.686364 | C28: =B11 -> 281500 | D28: =C28/B28 -> 12980.507 | E28: =D28*50 -> 649025.36 | F28: =B28*B14-C28 -> 195600
A29: Material cost +15% | B29: =B9-0.15*B4 -> 18.663636 | C29: =B11 -> 281500 | D29: =C29/B29 -> 15082.806 | E29: =D29*B8 -> 723974.67 | F29: =B29*B14-C29 -> 129100
A30: Fixed costs +10% | B30: =B9 -> 19.686364 | C30: =B11*1.1 -> 309650 | D30: =C30/B30 -> 15729.162 | E30: =D30*B8 -> 754999.77 | F30: =B30*B14-C30 -> 123450
A33: Profit at full capacity (units) | B33: =Inputs!$B$7 -> 27000
A34: Profit at full capacity (Rs) | B34: =B33*B9-B11 -> 250031.82
A35: Target profit (Rs) | B35: 200000 | C35: Input - owner's possible target (assumption)
A36: Units required for target profit | B36: =(B11+B35)/B9 -> 24458.555
